{"body_text": "How does binding a soul to an armor suit allow the suit to move? We know a couple of characters whose souls are bound to armor suits, e.g. Alphonse or Barry the Chopper. It was explicitly shown that the armor suits have nothing inside - which means they are just pieces of metal with an rune that binds the soul to the armor. \n\nSo how are they able to move at all, not to mention that they have significant physical strength and agility?\n", "post_id": "3854", "cluster_id": 216, "novelty": true, "order": 0}
{"body_text": "How is Alphonse Elric able to see? How is Alphonse Elric ( And all the other souls affixed to objects ) able to see ?\nContains Spoilers\nAlphonse soul got affixed to a armor but his real body still remains in the void. So how is he able to see through the piece of armor? And does this not collide with his real body's vision. All his other sense's such as feeling, taste are removed. And he also has the inability to sleep. So why does his vision remain?\n", "post_id": "7050", "cluster_id": 216, "novelty": true, "order": 1}
