{"body_text": "Why did the Hunter x Hunter manga go on hiatus? I think the Hunter x Hunter manga has been on hiatus for months now; does anyone know the reason for the hiatus? Is the author planning to continue the series?\n", "post_id": "4751", "cluster_id": 508, "novelty": true, "order": 0}
{"body_text": "Why wasn't Hunter x Hunter chapter 350 released yet? Does anyone here know why Hunter x Hunter chapter 350 has not been released yet?\nWhen is it coming out? I would be grateful for any answers or comments you are able to provide.\n", "post_id": "15571", "cluster_id": 508, "novelty": false, "order": 1}
