{"body_text": "How do Luffy's Gear attacks work? Might just be me missing an explanation part in the manga, or just not properly understanding at the time. But how does Luffy's Gear 2nd and 3rd attacks work? \n\n", "post_id": "8177", "cluster_id": 778, "novelty": true, "order": 0}
{"body_text": "In the Dressrosa Arc, why doesn't Luffy use Gear Second to quickly reach Doflamingo? In the Dressrosa Arc, Luffy runs or rides constantly in order to reach Doflamingo - first he rides the bull Moocy, then he rides Cabbage's horse, and later starts running himself. \nWhy doesn't Luffy use his Gear Second instead to quickly reach Doflamingo? We have seen how swiftly he moves and jumps from one place to another in Gear Second. \nI get the point that he was carrying Law with him, but I guess that shouldn't be problem for him.\n", "post_id": "22004", "cluster_id": 778, "novelty": true, "order": 1}
