{"body_text": "Is Dragon Ball Super considered canon? Is Dragon Ball Super considered an original works by Akira Toriyama?\n", "post_id": "23029", "cluster_id": 922, "novelty": true, "order": 0}
{"body_text": "Where in the Dragon Ball timeline is the Super series? At the end of the Dragon Ball series we can see Goku fly off with Uub towards his village to train. There had been years of peace so we see Goten and Trunks all grown to teenagers, yet in the Super series they are still young. So it seems that Uub does not exist yet and the Super series does not follow directly after the Dragon Ball series, the same way the GT series did. So where does it fit in? When does the Super series take place?\n", "post_id": "23063", "cluster_id": 922, "novelty": true, "order": 1}
