{"body_text": "Where is this picture from? How do I use Reverse Image Search to find the source of an anime/manga image? So I see an image from what I believe is from either an anime or manga. What are some ways that I can go about finding what series it's from?\nTry these options:\n\nGoogle reverse image search (browser built-in support and plugins)\nOther reverse image search engines: TinEye, SauceNao, iqdb\nTechnique: Cropping the image\nAnimated GIF: Picking the right frame\n\n", "post_id": "21618", "cluster_id": 1351, "novelty": true, "order": 0}
{"body_text": "What is this manga where a girl is told that she's never been seen only as a friend? \nThis picture is really cute so I want to know what manga this is so please help me thank you for your consideration.\n", "post_id": "21599", "cluster_id": 1351, "novelty": false, "order": 1}
