{"body_text": "What are the reference of Heaven's Lost Property to the Greek Mythology? In Heaven's Lost property, there are some obvious references to Greek Mythology, such as Zeus' cannon which is obviously linked to the Greek God Zeus.\n\nWhat are the references to Sora No Otoshimono in Greek Mythology? Are there any links between the references and the character designs?\n\nThis question is intended to be self-answered, but other hints and recommendations are welcome.\n", "post_id": "28451", "cluster_id": 1563, "novelty": true, "order": 0}
{"body_text": "What are the many references Dragon Ball Series makes to other franchises/people? I was watching Dragon Ball and couldn\u2019t help noticing the reference to Bruce Lee and Jackie Chan  in the World Tournament Saga. \nSo my question is, are their more such references in the series or this is as far as it gets?\n", "post_id": "29186", "cluster_id": 1563, "novelty": true, "order": 1}
